django_log_to_telegram/__init__.py
django_log_to_telegram/log.py
django_log_to_telegram/models.py
django_log_to_telegram/management/__init__.py
django_log_to_telegram/management/commands/__init__.py
django_log_to_telegram/management/commands/send_test_message.py
django_log_to_telegram/migrations/0001_initial.py
django_log_to_telegram/migrations/0002_auto_20200123_1520.py
django_log_to_telegram/migrations/__init__.py
django_log_to_telegram-2023.12.18.dist-info/METADATA
django_log_to_telegram-2023.12.18.dist-info/WHEEL
django_log_to_telegram-2023.12.18.dist-info/licenses/LICENSE
django_log_to_telegram-2023.12.18.dist-info/RECORD
