Metadata-Version: 2.1
Name: django-log-to-telegram
Version: 2023.12.18
Summary: a simple logger that sends 500 exceptions to a Telegram bot of your choice.
Project-URL: Homepage, https://baltig.cnr.it/luigi.mazarivillanova/django_ggupload
Project-URL: Issues, https://baltig.cnr.it/luigi.mazarivillanova/django_ggupload/-/issues
Author-email: Luigi Mazari Villanova <luigi.mazari@gmail.com>
License-File: LICENSE
Classifier: Development Status :: 4 - Beta
Classifier: Environment :: Web Environment
Classifier: Framework :: Django
Classifier: Framework :: Django :: 1.9
Classifier: Framework :: Django :: 2.0
Classifier: Framework :: Django :: 2.1
Classifier: Framework :: Django :: 4
Classifier: Intended Audience :: Developers
Classifier: License :: OSI Approved :: GNU General Public License v3 (GPLv3)
Classifier: Operating System :: OS Independent
Classifier: Programming Language :: Python
Classifier: Programming Language :: Python :: 3
Classifier: Topic :: Internet :: WWW/HTTP
Classifier: Topic :: Internet :: WWW/HTTP :: Site Management
Classifier: Topic :: Scientific/Engineering
Requires-Python: >3.0
Requires-Dist: django>1.9
Requires-Dist: requests
